sphinx_exec_code/__const__.py
sphinx_exec_code/__init__.py
sphinx_exec_code/__version__.py
sphinx_exec_code/code_exec.py
sphinx_exec_code/code_exec_error.py
sphinx_exec_code/code_format.py
sphinx_exec_code/sphinx_api.py
sphinx_exec_code/sphinx_exec.py
sphinx_exec_code/sphinx_spec.py
sphinx_exec_code/configuration/__init__.py
sphinx_exec_code/configuration/base.py
sphinx_exec_code/configuration/flag_config.py
sphinx_exec_code/configuration/path_config.py
sphinx_exec_code/configuration/values.py
sphinx_exec_code-0.16.dist-info/licenses/LICENSE
sphinx_exec_code-0.16.dist-info/METADATA
sphinx_exec_code-0.16.dist-info/WHEEL
sphinx_exec_code-0.16.dist-info/top_level.txt
sphinx_exec_code-0.16.dist-info/RECORD
