Metadata-Version: 2.4
Name: sphinx-exec-code
Version: 0.16
Summary: Execute code blocks in Sphinx and display the output
Home-page: https://github.com/spacemanspiff2007/sphinx-exec-code
Author: spaceman_spiff
Project-URL: GitHub, https://github.com/spacemanspiff2007/sphinx-exec-code
Project-URL: Documentation, https://sphinx-exec-code.readthedocs.io/
Keywords: sphinx,execute,exec,code
Classifier: Development Status :: 5 - Production/Stable
Classifier: Intended Audience :: Developers
Classifier: Framework :: Sphinx :: Extension
Classifier: License :: OSI Approved :: Apache Software License
Classifier: Natural Language :: English
Classifier: Operating System :: OS Independent
Classifier: Programming Language :: Python :: 3.8
Classifier: Programming Language :: Python :: 3.9
Classifier: Programming Language :: Python :: 3.10
Classifier: Programming Language :: Python :: 3.11
Classifier: Programming Language :: Python :: 3.12
Classifier: Programming Language :: Python :: 3.13
Classifier: Programming Language :: Python :: 3 :: Only
License-File: LICENSE
Dynamic: author
Dynamic: classifier
Dynamic: description
Dynamic: description-content-type
Dynamic: home-page
Dynamic: keywords
Dynamic: license-file
Dynamic: project-url
Dynamic: summary
